Orr_Sommerfeld/OS.py
Orr_Sommerfeld/Orr_Sommerfeld.py
Orr_Sommerfeld/__init__.py
Orr_Sommerfeld-0.0.8.dist-info/LICENSE
Orr_Sommerfeld-0.0.8.dist-info/METADATA
Orr_Sommerfeld-0.0.8.dist-info/WHEEL
Orr_Sommerfeld-0.0.8.dist-info/top_level.txt
Orr_Sommerfeld-0.0.8.dist-info/RECORD
