Metadata-Version: 2.1
Name: Orr-Sommerfeld
Version: 0.0.8
Summary: La presente libreria permite analizar Orr Sommerfeld temporal y espacial
Home-page: https://gitlab/publish
Author: Fernando Scarafia
Author-email: fernando.scarafia@ib.edu.ar
License: UNKNOWN
Platform: UNKNOWN
Classifier: Programming Language :: Python :: 3
Classifier: Operating System :: OS Independent
Classifier: License :: OSI Approved :: MIT License
License-File: LICENSE
